rfc9457/__init__.py
rfc9457/openapi.py
rfc9457/py.typed
rfc9457-0.4.0.dist-info/METADATA
rfc9457-0.4.0.dist-info/WHEEL
rfc9457-0.4.0.dist-info/licenses/LICENSE
rfc9457-0.4.0.dist-info/RECORD
